[
    {
        "company": "NVIDIA",
        "name": "[NVIDIA]8-K(2023-06-27)",
        "url": "https://www.sec.gov/Archives/edgar/data/1045810/000104581023000146/nvda-20230622.htm",
        "content": "0001045810false00010458102023-06-222023-06-22",
        "updated_at": "2023-06-27",
        "category": "edgar"
    },
    {
        "company": "NVIDIA",
        "name": "[NVIDIA]8-K(2023-06-27)",
        "url": "https://www.sec.gov/Archives/edgar/data/1045810/000104581023000146/nvda-20230622.htm",
        "content": "| Delaware | 0-23985 | 94-3177549 |\n| (State or other jurisdiction | (Commission | (IRS Employer |\n| of incorporation) | File Number) | Identification No.) |",
        "updated_at": "2023-06-27",
        "category": "edgar"
    },
    {
        "company": "NVIDIA",
        "name": "[NVIDIA]8-K(2023-06-27)",
        "url": "https://www.sec.gov/Archives/edgar/data/1045810/000104581023000146/nvda-20230622.htm",
        "content": "Check the appropriate box below if the Form 8-K filing is intended to simultaneously satisfy the filing obligation of the registrant under any of the following provisions:☐ Written communications pursuant to Rule 425 under the Securities Act (17 CFR 230.425)☐ Soliciting material pursuant to Rule 14a-12 under the Exchange Act (17 CFR 240.14a-12)☐ Pre-commencement communications pursuant to Rule 14d-2(b) under the Exchange Act (17 CFR 240.14d-2(b))☐ Pre-commencement communications pursuant to Rule 13e-4(c) under the Exchange Act (17 CFR 240.13e-4(c))",
        "updated_at": "2023-06-27",
        "category": "edgar"
    },
    {
        "company": "NVIDIA",
        "name": "[NVIDIA]8-K(2023-06-27)",
        "url": "https://www.sec.gov/Archives/edgar/data/1045810/000104581023000146/nvda-20230622.htm",
        "content": "| Title of each class | Trading Symbol(s) | Name of each exchange on which registered |\n| Common Stock, $0.001 par value per share | NVDA | The Nasdaq Global Select Market |",
        "updated_at": "2023-06-27",
        "category": "edgar"
    },
    {
        "company": "NVIDIA",
        "name": "[NVIDIA]8-K(2023-06-27)",
        "url": "https://www.sec.gov/Archives/edgar/data/1045810/000104581023000146/nvda-20230622.htm",
        "content": "Indicate by check mark whether the registrant is an emerging growth company as defined in Rule 405 of the Securities Act of 1933 (§230.405 of this chapter) or Rule 12b-2 of the Securities Exchange Act of 1934 (§240.12b-2 of this chapter).      Emerging Growth Company ☐ If an emerging growth company, indicate by check mark if the registrant has elected not to use the extended transition period for complying with any new or revised financial accounting standards provided pursuant to Section 13(a) of the Exchange Act. ☐",
        "updated_at": "2023-06-27",
        "category": "edgar"
    },
    {
        "company": "NVIDIA",
        "name": "[NVIDIA]8-K(2023-06-27)",
        "url": "https://www.sec.gov/Archives/edgar/data/1045810/000104581023000146/nvda-20230622.htm",
        "content": "On June 22, 2023, at the 2023 Annual Meeting of Stockholders of NVIDIA Corporation, or the 2023 Annual Meeting, the following proposals were adopted by the margin indicated. Proxies for the 2023 Annual Meeting were solicited pursuant to Section 14(a) of the Securities Exchange Act of 1934, as amended, and there was no solicitation in opposition of management’s solicitation.1.    Stockholders approved the election of each of our thirteen (13) director nominees to hold office until the 2024 Annual Meeting of Stockholders of NVIDIA Corporation and until his or her successor is elected or appointed.  The results of the voting were as follows:\n| | a. Robert K. Burgess |\n| Number of shares For | 1625854250 |\n| Number of shares Against | 55516966 |\n| Number of shares Abstaining | 2085730 |\n| Number of Broker Non-Votes | 286066136 |",
        "updated_at": "2023-06-27",
        "category": "edgar"
    },
    {
        "company": "NVIDIA",
        "name": "[NVIDIA]8-K(2023-06-27)",
        "url": "https://www.sec.gov/Archives/edgar/data/1045810/000104581023000146/nvda-20230622.htm",
        "content": "| | b. Tench Coxe |\n| Number of shares For | 1541282586 |\n| Number of shares Against | 140103871 |\n| Number of shares Abstaining | 2070489 |\n| Number of Broker Non-Votes | 286066136 |",
        "updated_at": "2023-06-27",
        "category": "edgar"
    },
    {
        "company": "NVIDIA",
        "name": "[NVIDIA]8-K(2023-06-27)",
        "url": "https://www.sec.gov/Archives/edgar/data/1045810/000104581023000146/nvda-20230622.htm",
        "content": "| | c. John O. Dabiri |\n| Number of shares For | 1651249399 |\n| Number of shares Against | 30122052 |\n| Number of shares Abstaining | 2085495 |\n| Number of Broker Non-Votes | 286066136 |",
        "updated_at": "2023-06-27",
        "category": "edgar"
    },
    {
        "company": "NVIDIA",
        "name": "[NVIDIA]8-K(2023-06-27)",
        "url": "https://www.sec.gov/Archives/edgar/data/1045810/000104581023000146/nvda-20230622.htm",
        "content": "| | d. Persis S. Drell |\n| Number of shares For | 1623178165 |\n| Number of shares Against | 58242340 |\n| Number of shares Abstaining | 2036441 |\n| Number of Broker Non-Votes | 286066136 |",
        "updated_at": "2023-06-27",
        "category": "edgar"
    },
    {
        "company": "NVIDIA",
        "name": "[NVIDIA]8-K(2023-06-27)",
        "url": "https://www.sec.gov/Archives/edgar/data/1045810/000104581023000146/nvda-20230622.htm",
        "content": "| | e. Jen-Hsun Huang |\n| Number of shares For | 1647312653 |\n| Number of shares Against | 32866873 |\n| Number of shares Abstaining | 3277420 |\n| Number of Broker Non-Votes | 286066136 |",
        "updated_at": "2023-06-27",
        "category": "edgar"
    },
    {
        "company": "NVIDIA",
        "name": "[NVIDIA]8-K(2023-06-27)",
        "url": "https://www.sec.gov/Archives/edgar/data/1045810/000104581023000146/nvda-20230622.htm",
        "content": "| | f. Dawn Hudson |\n| Number of shares For | 1630929129 |\n| Number of shares Against | 50515840 |\n| Number of shares Abstaining | 2011977 |\n| Number of Broker Non-Votes | 286066136 |",
        "updated_at": "2023-06-27",
        "category": "edgar"
    },
    {
        "company": "NVIDIA",
        "name": "[NVIDIA]8-K(2023-06-27)",
        "url": "https://www.sec.gov/Archives/edgar/data/1045810/000104581023000146/nvda-20230622.htm",
        "content": "| | g. Harvey C. Jones |\n| Number of shares For | 1485702770 |\n| Number of shares Against | 195712370 |\n| Number of shares Abstaining | 2041806 |\n| Number of Broker Non-Votes | 286066136 |",
        "updated_at": "2023-06-27",
        "category": "edgar"
    },
    {
        "company": "NVIDIA",
        "name": "[NVIDIA]8-K(2023-06-27)",
        "url": "https://www.sec.gov/Archives/edgar/data/1045810/000104581023000146/nvda-20230622.htm",
        "content": "| | h. Michael G. McCaffery |\n| Number of shares For | 1666592304 |\n| Number of shares Against | 14686036 |\n| Number of shares Abstaining | 2178606 |\n| Number of Broker Non-Votes | 286066136 |",
        "updated_at": "2023-06-27",
        "category": "edgar"
    },
    {
        "company": "NVIDIA",
        "name": "[NVIDIA]8-K(2023-06-27)",
        "url": "https://www.sec.gov/Archives/edgar/data/1045810/000104581023000146/nvda-20230622.htm",
        "content": "| | i. Stephen C. Neal |\n| Number of shares For | 1500500287 |\n| Number of shares Against | 180807940 |\n| Number of shares Abstaining | 2148719 |\n| Number of Broker Non-Votes | 286066136 |",
        "updated_at": "2023-06-27",
        "category": "edgar"
    },
    {
        "company": "NVIDIA",
        "name": "[NVIDIA]8-K(2023-06-27)",
        "url": "https://www.sec.gov/Archives/edgar/data/1045810/000104581023000146/nvda-20230622.htm",
        "content": "| | j. Mark L. Perry |\n| Number of shares For | 1506459534 |\n| Number of shares Against | 174857324 |\n| Number of shares Abstaining | 2140088 |\n| Number of Broker Non-Votes | 286066136 |",
        "updated_at": "2023-06-27",
        "category": "edgar"
    },
    {
        "company": "NVIDIA",
        "name": "[NVIDIA]8-K(2023-06-27)",
        "url": "https://www.sec.gov/Archives/edgar/data/1045810/000104581023000146/nvda-20230622.htm",
        "content": "| | k. A. Brooke Seawell |\n| Number of shares For | 1527924819 |\n| Number of shares Against | 152477701 |\n| Number of shares Abstaining | 3054426 |\n| Number of Broker Non-Votes | 286066136 |",
        "updated_at": "2023-06-27",
        "category": "edgar"
    },
    {
        "company": "NVIDIA",
        "name": "[NVIDIA]8-K(2023-06-27)",
        "url": "https://www.sec.gov/Archives/edgar/data/1045810/000104581023000146/nvda-20230622.htm",
        "content": "| | l. Aarti Shah |\n| Number of shares For | 1676241988 |\n| Number of shares Against | 5161064 |\n| Number of shares Abstaining | 2053894 |\n| Number of Broker Non-Votes | 286066136 |",
        "updated_at": "2023-06-27",
        "category": "edgar"
    },
    {
        "company": "NVIDIA",
        "name": "[NVIDIA]8-K(2023-06-27)",
        "url": "https://www.sec.gov/Archives/edgar/data/1045810/000104581023000146/nvda-20230622.htm",
        "content": "| | m. Mark A. Stevens |\n| Number of shares For | 1562037938 |\n| Number of shares Against | 119338471 |\n| Number of shares Abstaining | 2080537 |\n| Number of Broker Non-Votes | 286066136 |",
        "updated_at": "2023-06-27",
        "category": "edgar"
    },
    {
        "company": "NVIDIA",
        "name": "[NVIDIA]8-K(2023-06-27)",
        "url": "https://www.sec.gov/Archives/edgar/data/1045810/000104581023000146/nvda-20230622.htm",
        "content": "2.    Stockholders approved, on an advisory basis, the compensation of our named executive officers as disclosed in our definitive proxy statement for the 2023 Annual Meeting filed with the Securities and Exchange Commission on May 8, 2023. The results of the voting were as follows:\n| Number of shares For | 1.54445e+09 |\n| Number of shares Against | 1.23718e+08 |\n| Number of shares Abstaining | 1.52918e+07 |\n| Number of Broker Non-Votes | 2.86066e+08 |",
        "updated_at": "2023-06-27",
        "category": "edgar"
    },
    {
        "company": "NVIDIA",
        "name": "[NVIDIA]8-K(2023-06-27)",
        "url": "https://www.sec.gov/Archives/edgar/data/1045810/000104581023000146/nvda-20230622.htm",
        "content": "3.     Stockholders approved, on an advisory basis, the frequency of holding an advisory vote on the compensation of our named executive officers. The results of the voting were as follows:\n| Number of shares for 1 Year | 1.66424e+09 |\n| Number of shares for 2 Years | 2.06294e+06 |\n| Number of shares for 3 Years | 1.49236e+07 |\n| Number of shares Abstaining | 2.22906e+06 |\n| Number of Broker Non-Votes | 2.86066e+08 |",
        "updated_at": "2023-06-27",
        "category": "edgar"
    },
    {
        "company": "NVIDIA",
        "name": "[NVIDIA]8-K(2023-06-27)",
        "url": "https://www.sec.gov/Archives/edgar/data/1045810/000104581023000146/nvda-20230622.htm",
        "content": "Based on the voting results, we have determined to provide for an annual advisory vote on the compensation of our named executive officers.4.    Stockholders approved the ratification of the selection of PricewaterhouseCoopers LLP as our independent registered accounting firm for our fiscal year ending January 28, 2024. The results of the voting were as follows:\n| Number of shares For | 1938914100 |\n| Number of shares Against | 28443041 |\n| Number of shares Abstaining | 2165941 |\n| Number of Broker Non-Votes | — |",
        "updated_at": "2023-06-27",
        "category": "edgar"
    },
    {
        "company": "NVIDIA",
        "name": "[NVIDIA]8-K(2023-06-27)",
        "url": "https://www.sec.gov/Archives/edgar/data/1045810/000104581023000146/nvda-20230622.htm",
        "content": "Pursuant to the requirements of the Securities Exchange Act of 1934, the registrant has duly caused this report to be signed on its behalf by the undersigned hereunto duly authorized. NVIDIA CorporationDate: June 27, 2023By: /s/ Rebecca Peters                                                        Rebecca PetersVice President, Deputy General Counsel and Assistant Secretary",
        "updated_at": "2023-06-27",
        "category": "edgar"
    }
]